{
  "name": "Болото Отчаяния",
  "biome": "water",
  "danger": 15,
  "map": [
    "########################################",
    "#......................................#",
    "#..~~....~.....~~...~.....~.~....~.~...#",
    "#.~...~~~~~~..~.~.~~.~.......~...~~~~..#",
    "#.........~....~~.......~....~....~....#",
    "#....~.......~...~.........~...........#",
    "#..~~..~......~.....~.....~..~.~.......#",
    "#.~~...~~~~~...~~.......~~....f~.~.....#",
    "#....~.~...................~.~....~....#",
    "#..............~..~~~.~~.....~.~.~~....#",
    "#.~~.....~....~...~~..~....~...~.~.....#",
    "#........~...~~.....~.~....~......~....#",
    "#..........~..~................~..~.~..#",
    "4.....~..~~........~~~~...~............2",
    "#......~~..~..............~.~..~~....~.#",
    "#..................~~....~....~........#",
    "#...~...~...~.............~.~.~~.....~.#",
    "#......~...~.~...~..~....~~..~.~~.~.~..#",
    "#..~~...........~..........~~..~.~.~...#",
    "#...~..........~........~......~~j.....#",
    "#..~~..............~....~~.............#",
    "#............~...~.~.~.....~~..~.~.....#",
    "#.....~....~...~..........~........~~..#",
    "#......~~..~.~...~..~.....~.~...~......#",
    "#...................3..................#",
    "########################################"
  ],
  "entry": [
    3,
    13
  ],
  "npcs": {},
  "exits": {
    "4": "iceopera",
    "2": "bonewaste",
    "3": "jungle"
  },
  "boss": null,
  "wind": false,
  "fish": true,
  "monsters": [
    [
      "Кислотная Медуза",
      26,
      7
    ],
    [
      "Топляк-Зомби",
      34,
      8
    ],
    [
      "Злая Рыбёшка",
      20,
      6
    ],
    [
      "Болотная Пиявка",
      18,
      5
    ]
  ],
  "min_level": 11,
  "nodes": {}
}